sphinx_orange_book_theme/__init__.py
sphinx_orange_book_theme/static/styles/sphinx-orange-book-theme-colors.css
sphinx_orange_book_theme/static/styles/sphinx-orange-book-theme.css
sphinx_orange_book_theme/theme.conf
sphinx_orange_book_theme-0.19.0.dist-info/METADATA
sphinx_orange_book_theme-0.19.0.dist-info/WHEEL
sphinx_orange_book_theme-0.19.0.dist-info/entry_points.txt
sphinx_orange_book_theme-0.19.0.dist-info/licenses/LICENSE.txt
sphinx_orange_book_theme-0.19.0.dist-info/RECORD
