Metadata-Version: 2.4
Name: sphinx-orange-book-theme
Version: 0.19.0
Summary: An orange version of sphinx-book-theme.
License: MIT
License-File: LICENSE.txt
Keywords: sphinx
Author: Kenta Kabashima
Author-email: kenta_program37@hotmail.co.jp
Requires-Python: >=3.12,<3.15
Classifier: Development Status :: 4 - Beta
Classifier: Framework :: Sphinx :: Theme
Classifier: Intended Audience :: Developers
Classifier: License :: OSI Approved :: MIT License
Classifier: Programming Language :: Python :: 3
Classifier: Programming Language :: Python :: 3.12
Classifier: Programming Language :: Python :: 3.13
Classifier: Programming Language :: Python :: 3.14
Classifier: Topic :: Documentation :: Sphinx
Classifier: Topic :: Software Development :: Documentation
Requires-Dist: sphinx (>=8.2.3)
Requires-Dist: sphinx-book-theme (>=1.1.4,<2.0.0)
Project-URL: Documentation, https://sphinx-orange-book-theme-musicscience37projects--1dc46f9ab80e60.gitlab.io/
Project-URL: Homepage, https://gitlab.com/MusicScience37Projects/utility-libraries/sphinx-orange-book-theme
Project-URL: Repository, https://gitlab.com/MusicScience37Projects/utility-libraries/sphinx-orange-book-theme.git
